src/inst_rom.v
module inst_rom (
    input wire [7:0] address ,
    output reg [7:0] instruction_byte = 0
);

reg [7:0] mem [0:255];
        integer i;
initial begin

    for (i = 0 ; i < 256 ; i = i+1 ) begin
        mem[i] = 0;
    end
end
initial begin
// 1. add 3
    mem[8'h01] = 8'h01; // ADD opcode (1)
    mem[8'h02] = 8'h03; // operand = 3

    // --- LOOP START (Address 0x03) ---
    // 2. sub 1
    mem[8'h03] = 8'h02; // SUB opcode (2)
    mem[8'h04] = 8'h01; // operand = 1

    // 3. jnz to address 0x03
    mem[8'h05] = 8'h0F; // JNZ opcode (15 / hex 0F)
    mem[8'h06] = 8'h03; // target address = 0x03 (loops back to SUB)
    // --- LOOP END ---

    // 4. out to address 5 (runs when accumulator hits 0)
    mem[8'h07] = 8'h05; // OUT opcode (5)
    mem[8'h08] = 8'h05; // target RAM address = 5

    // 5. clean
    mem[8'h09] = 8'h06; // CLEAN opcode (6)
    mem[8'h0A] = 8'h00; // operand = 0
end

always @(*) begin
    instruction_byte = mem[address];
end
    
endmodule

src/prog_cntr.v
module prog_cntr(
    input wire clk,
    input wire [7:0] instruction_byte,
    output reg [7:0] address = 1,
    output reg [3:0] op_code = 0,
    output reg [7:0] operand,
    input wire start_enable,
    output reg we = 0,
    output reg [7:0] counter = 0,
    output reg [7:0] rom_address = 0,
    input wire [7:0] rom_data_in,
    input wire zero_flag
);

reg [7:0] op ;
reg [7:0] num ;
reg [7:0] rom_data ;

localparam inst_1 = 0 ;
localparam inst_2 = 1 ;
localparam exe = 2 ;
localparam mem_wait = 3;
localparam mem_exec = 4;

localparam ADD = 8'd1 ;
localparam SUB = 8'd2;
localparam SHIFT_LEFT = 8'd3;
localparam SHIFT_RIGHT = 8'd4;
localparam OUT = 8'd5;
localparam CLEAN = 8'd6;
localparam JUMP = 8'd10;
localparam ADD_MEM = 8'd11;
localparam SUB_MEM = 8'd12;
localparam SHIFT_LEFT_MEM = 8'd13;
localparam SHIFT_RIGHT_MEM = 8'd14;
localparam JNZ = 8'd15 ;
localparam JZ = 8'd16 ;

reg [2:0] state = 2'd0 ;


always @(posedge clk ) begin
    if(start_enable)begin
        case (state)
            inst_1 : begin
                op <= instruction_byte;
                state <= inst_2;
                address <= address + 8'd1;
                we <= 0;         
            end
            inst_2 : begin
                num <= instruction_byte;
                state <= exe;
            end
            exe : begin
                counter <= counter + 8'd1;
                if(op < 8'd7) begin
                    op_code <= (op & 4'hF);
                    operand <= num;
                    address <= address + 8'd1;
                    state <= inst_1;
                    num <= 0;
                    op <= 0;
                    we <= 1;
                end
                else if(op >= 8'd10) begin
                    case (op)
                        ADD_MEM : begin
                            state <= mem_wait;
                            rom_address <= num;
                            op <= ADD;
                        end
                        SUB_MEM : begin
                            state <= mem_wait;
                            rom_address <= num;
                            op <= SUB;
                        end
                        SHIFT_LEFT_MEM : begin
                            state <= mem_wait;
                            rom_address <= num;
                            op <= SHIFT_LEFT;
                        end
                        SHIFT_RIGHT_MEM : begin
                            state <= mem_wait;
                            rom_address <= num;
                            op <= SHIFT_RIGHT;
                        end
                        JUMP : begin
                            address <= num;
                            state <= inst_1;
                            num <= 0;
                            op <= 0;
                        end
                        JNZ : begin
                            if (~zero_flag) begin
                                address <= num;
                                state <= inst_1;
                                num <= 0;
                                op <= 0;
                            end
                            else begin
                                address <= address + 8'd1;
                                state <= inst_1;
                            end
                        end
                        JZ : begin
                            if (zero_flag) begin
                                address <= num;
                                state <= inst_1;
                                num <= 0;
                                op <= 0;
                            end
                            else begin
                                address <= address + 8'd1;
                                state <= inst_1;
                            end
                        end
                        default: begin 
                            state <= inst_1;
                        end
                    endcase
                end
            end
            mem_wait : begin
                state <= mem_exec;
                //num <= rom_data_in;
            end
            mem_exec : begin
                state <= inst_1;
                operand <= rom_data_in;
                op_code <= op;
                address <= address + 8'd1;
                num <= 0;
                op <= 0;
                we <= 1;
                rom_address <= 0;
            end  
            default: begin 
                state <= inst_1;
                op_code <= 0;
                operand <= 0;
            end
        endcase
    end
end
endmodule

src/accumulator.v
module accumulator(
    input wire clk,
    input wire [3:0] op,
    input wire [7:0] num,
    output reg [7:0] result = 0,
    input wire we,
    output reg [7:0] address_mem = 0,
    output wire zero_flag,
    output reg we_ram
);

reg [7:0] data = 8'd0 ;

localparam ADD = 4'd1 ;
localparam SUB = 4'd2;
localparam SHIFT_LEFT = 4'd3;
localparam SHIFT_RIGHT = 4'd4;
localparam OUT = 4'd5;
localparam CLEAN = 4'd6;
localparam AND = 4'd7;
localparam OR = 4'd8;
localparam NOT = 4'd9;

assign zero_flag = (data == 0) ? 1 : 0;

always @(posedge clk ) begin
    we_ram <= 0;
    if (op != 0 && we) begin
        case (op)
            ADD : begin
                data <= data + num;
            end
            SUB : begin
                data <= data - num;
            end
            SHIFT_LEFT : begin
                data <= data << (num & 8'h7);
            end
            SHIFT_RIGHT : begin
                data <= data >> (num & 8'h7);
            end
            AND : begin
                data <= data & num;
            end
            OR : begin
                data <= data | num;
            end
            NOT : begin
                data <= ~num;
            end
            OUT : begin
                result <= data;
                address_mem <= num;
                we_ram <= 1;
            end
            CLEAN : begin
                result <= 8'd0;
                data <= 8'd0;
            end 
            default: begin
                data <= data;
            end
        endcase
    end
    else begin
        result <= result;
    end
end
endmodule

src/ram.v
module ram(
    input wire clk,
    input wire we,
    input wire [7:0] addr,
    input wire [7:0] d_in,
    output reg [7:0] d_out = 0
);

reg [7:0] mem [0:255];

integer i;

initial begin
    for(i=0 ; i<256 ; i=i+1)
        mem[i] = 8'd00;
end


always @(posedge clk ) begin
    
    if(addr != 0)
    begin
        d_out <= mem[addr];
        if (we) begin
            mem[addr] <= d_in;
        end
    end    
    else begin
        d_out <= 0;
    end
    

end
endmodule

src/tb_cpu.v
`timescale 1ns/1ps

module tb_cpu();

reg clk;
wire we_ram;
wire [7:0] address_ram;
wire [7:0] d_out_accu;
wire [7:0] d_out_ram;
wire [3:0] operation;
wire [7:0] operand;
wire we_accu;
wire zero_flag;
wire [7:0] rom_out;
wire [7:0] rom_address;
reg start_enable;
wire [7:0] counter;
wire [7:0] address_ram_from_pc;
wire [7:0] address_ram_from_accu;

assign address_ram = we_ram ? address_ram_from_accu : address_ram_from_pc;




ram ram_sim(
    .clk(clk),
    .we(we_ram),
    .addr(address_ram),
    .d_in(d_out_accu),
    .d_out(d_out_ram)
);
accumulator accu_sim(
    .clk(clk),
    .op(operation),
    .num(operand),
    .result(d_out_accu),
    .we(we_accu),
    .address_mem(address_ram_from_accu),
    .zero_flag(zero_flag),
    .we_ram(we_ram)
);
prog_cntr pc_sim(
    .clk(clk),
    .instruction_byte(rom_out),
    .address(rom_address) ,
    .op_code(operation),
    .operand(operand),
    .start_enable(start_enable),
    .we(we_accu),
    .counter(counter),
    .rom_address(address_ram_from_pc),
    .rom_data_in(d_out_ram),
    .zero_flag(zero_flag)
);
inst_rom inst_rom_sim(
    .address(rom_address) ,
    .instruction_byte(rom_out)
);

always #70 clk = ~clk;

initial begin
    clk = 0;
    start_enable = 0;
    #100
    start_enable = 1;
    @(posedge clk);
    wait (counter == 100);
    $finish;
end
integer i;
initial begin
    $dumpfile("tb_cpu.vcd");
    $dumpvars(0,tb_cpu);
    for (i = 0; i < 20; i = i + 1) begin
        $dumpvars(0, tb_cpu.ram_sim.mem[i]);
    end
end
endmodule

src/tb_cpu.vcd
$date
	Sun Sep 27 01:30:15 2026
$end
$version
	Icarus Verilog
$end
$timescale
	1ps
$end
$scope module tb_cpu $end
$var wire 1 ! zero_flag $end
$var wire 1 " we_ram $end
$var wire 1 # we_accu $end
$var wire 8 $ rom_out [7:0] $end
$var wire 8 % rom_address [7:0] $end
$var wire 4 & operation [3:0] $end
$var wire 8 ' operand [7:0] $end
$var wire 8 ( d_out_ram [7:0] $end
$var wire 8 ) d_out_accu [7:0] $end
$var wire 8 * counter [7:0] $end
$var wire 8 + address_ram_from_pc [7:0] $end
$var wire 8 , address_ram_from_accu [7:0] $end
$var wire 8 - address_ram [7:0] $end
$var reg 1 . clk $end
$var reg 1 / start_enable $end
$var integer 32 0 i [31:0] $end
$scope module accu_sim $end
$var wire 1 . clk $end
$var wire 1 ! zero_flag $end
$var wire 1 # we $end
$var wire 4 1 op [3:0] $end
$var wire 8 2 num [7:0] $end
$var parameter 4 3 ADD $end
$var parameter 4 4 AND $end
$var parameter 4 5 CLEAN $end
$var parameter 4 6 NOT $end
$var parameter 4 7 OR $end
$var parameter 4 8 OUT $end
$var parameter 4 9 SHIFT_LEFT $end
$var parameter 4 : SHIFT_RIGHT $end
$var parameter 4 ; SUB $end
$var reg 8 < address_mem [7:0] $end
$var reg 8 = data [7:0] $end
$var reg 8 > result [7:0] $end
$var reg 1 " we_ram $end
$upscope $end
$scope module inst_rom_sim $end
$var wire 8 ? address [7:0] $end
$var reg 8 @ instruction_byte [7:0] $end
$var integer 32 A i [31:0] $end
$upscope $end
$scope module pc_sim $end
$var wire 1 . clk $end
$var wire 8 B instruction_byte [7:0] $end
$var wire 1 / start_enable $end
$var wire 1 ! zero_flag $end
$var wire 8 C rom_data_in [7:0] $end
$var parameter 8 D ADD $end
$var parameter 8 E ADD_MEM $end
$var parameter 8 F CLEAN $end
$var parameter 8 G JNZ $end
$var parameter 8 H JUMP $end
$var parameter 8 I JZ $end
$var parameter 8 J OUT $end
$var parameter 8 K SHIFT_LEFT $end
$var parameter 8 L SHIFT_LEFT_MEM $end
$var parameter 8 M SHIFT_RIGHT $end
$var parameter 8 N SHIFT_RIGHT_MEM $end
$var parameter 8 O SUB $end
$var parameter 8 P SUB_MEM $end
$var parameter 32 Q exe $end
$var parameter 32 R inst_1 $end
$var parameter 32 S inst_2 $end
$var parameter 32 T mem_exec $end
$var parameter 32 U mem_wait $end
$var reg 8 V address [7:0] $end
$var reg 8 W counter [7:0] $end
$var reg 8 X num [7:0] $end
$var reg 8 Y op [7:0] $end
$var reg 4 Z op_code [3:0] $end
$var reg 8 [ operand [7:0] $end
$var reg 8 \ rom_address [7:0] $end
$var reg 3 ] state [2:0] $end
$var reg 1 # we $end
$upscope $end
$scope module ram_sim $end
$var wire 8 ^ addr [7:0] $end
$var wire 1 . clk $end
$var wire 8 _ d_in [7:0] $end
$var wire 1 " we $end
$var reg 8 ` d_out [7:0] $end
$var integer 32 a i [31:0] $end
$upscope $end
$upscope $end
$scope module tb_cpu $end
$scope module ram_sim $end
$var reg 8 b \mem[0] [7:0] $end
$upscope $end
$upscope $end
$scope module tb_cpu $end
$scope module ram_sim $end
$var reg 8 c \mem[1] [7:0] $end
$upscope $end
$upscope $end
$scope module tb_cpu $end
$scope module ram_sim $end
$var reg 8 d \mem[2] [7:0] $end
$upscope $end
$upscope $end
$scope module tb_cpu $end
$scope module ram_sim $end
$var reg 8 e \mem[3] [7:0] $end
$upscope $end
$upscope $end
$scope module tb_cpu $end
$scope module ram_sim $end
$var reg 8 f \mem[4] [7:0] $end
$upscope $end
$upscope $end
$scope module tb_cpu $end
$scope module ram_sim $end
$var reg 8 g \mem[5] [7:0] $end
$upscope $end
$upscope $end
$scope module tb_cpu $end
$scope module ram_sim $end
$var reg 8 h \mem[6] [7:0] $end
$upscope $end
$upscope $end
$scope module tb_cpu $end
$scope module ram_sim $end
$var reg 8 i \mem[7] [7:0] $end
$upscope $end
$upscope $end
$scope module tb_cpu $end
$scope module ram_sim $end
$var reg 8 j \mem[8] [7:0] $end
$upscope $end
$upscope $end
$scope module tb_cpu $end
$scope module ram_sim $end
$var reg 8 k \mem[9] [7:0] $end
$upscope $end
$upscope $end
$scope module tb_cpu $end
$scope module ram_sim $end
$var reg 8 l \mem[10] [7:0] $end
$upscope $end
$upscope $end
$scope module tb_cpu $end
$scope module ram_sim $end
$var reg 8 m \mem[11] [7:0] $end
$upscope $end
$upscope $end
$scope module tb_cpu $end
$scope module ram_sim $end
$var reg 8 n \mem[12] [7:0] $end
$upscope $end
$upscope $end
$scope module tb_cpu $end
$scope module ram_sim $end
$var reg 8 o \mem[13] [7:0] $end
$upscope $end
$upscope $end
$scope module tb_cpu $end
$scope module ram_sim $end
$var reg 8 p \mem[14] [7:0] $end
$upscope $end
$upscope $end
$scope module tb_cpu $end
$scope module ram_sim $end
$var reg 8 q \mem[15] [7:0] $end
$upscope $end
$upscope $end
$scope module tb_cpu $end
$scope module ram_sim $end
$var reg 8 r \mem[16] [7:0] $end
$upscope $end
$upscope $end
$scope module tb_cpu $end
$scope module ram_sim $end
$var reg 8 s \mem[17] [7:0] $end
$upscope $end
$upscope $end
$scope module tb_cpu $end
$scope module ram_sim $end
$var reg 8 t \mem[18] [7:0] $end
$upscope $end
$upscope $end
$scope module tb_cpu $end
$scope module ram_sim $end
$var reg 8 u \mem[19] [7:0] $end
$upscope $end
$upscope $end
$enddefinitions $end
$comment Show the parameter values. $end
$dumpall
b11 U
b100 T
b1 S
b0 R
b10 Q
b1100 P
b10 O
b1110 N
b100 M
b1101 L
b11 K
b101 J
b10000 I
b1010 H
b1111 G
b110 F
b1011 E
b1 D
b10 ;
b100 :
b11 9
b101 8
b1000 7
b1001 6
b110 5
b111 4
b1 3
$end
#0
$dumpvars
b0 u
b0 t
b0 s
b0 r
b0 q
b0 p
b0 o
b0 n
b0 m
b0 l
b0 k
b0 j
b0 i
b0 h
b0 g
b0 f
b0 e
b0 d
b0 c
b0 b
b100000000 a
b0 `
b0 _
b0 ^
b0 ]
b0 \
bx [
b0 Z
bx Y
bx X
b0 W
b1 V
b0 C
b1 B
b100000000 A
b1 @
b1 ?
b0 >
b0 =
b0 <
bx 2
b0 1
b10100 0
0/
0.
b0 -
b0 ,
b0 +
b0 *
b0 )
b0 (
bx '
b0 &
b1 %
b1 $
0#
x"
1!
$end
#70000
0"
1.
#100000
1/
#140000
0.
#210000
b11 $
b11 @
b11 B
b10 %
b10 ?
b10 V
b1 ]
b1 Y
1.
#280000
0.
#350000
b10 ]
b11 X
1.
#420000
0.
#490000
b10 $
b10 @
b10 B
1#
b0 Y
b0 X
b0 ]
b11 %
b11 ?
b11 V
b11 '
b11 2
b11 [
b1 &
b1 1
b1 Z
b1 *
b1 W
1.
#560000
0.
#630000
0!
b1 $
b1 @
b1 B
b11 =
0#
b100 %
b100 ?
b100 V
b1 ]
b10 Y
1.
#700000
0.
#770000
b10 ]
b1 X
1.
#840000
0.
#910000
b1111 $
b1111 @
b1111 B
1#
b0 Y
b0 X
b0 ]
b101 %
b101 ?
b101 V
b1 '
b1 2
b1 [
b10 &
b10 1
b10 Z
b10 *
b10 W
1.
#980000
0.
#1050000
b11 $
b11 @
b11 B
0#
b110 %
b110 ?
b110 V
b1 ]
b1111 Y
b10 =
1.
#1120000
0.
#1190000
b10 ]
b11 X
1.
#1260000
0.
#1330000
b10 $
b10 @
b10 B
b0 Y
b0 X
b0 ]
b11 %
b11 ?
b11 V
b11 *
b11 W
1.
#1400000
0.
#1470000
b1 $
b1 @
b1 B
b100 %
b100 ?
b100 V
b1 ]
b10 Y
1.
#1540000
0.
#1610000
b10 ]
b1 X
1.
#1680000
0.
#1750000
b1111 $
b1111 @
b1111 B
1#
b0 Y
b0 X
b0 ]
b101 %
b101 ?
b101 V
b100 *
b100 W
1.
#1820000
0.
#1890000
b11 $
b11 @
b11 B
0#
b110 %
b110 ?
b110 V
b1 ]
b1111 Y
b1 =
1.
#1960000
0.
#2030000
b10 ]
b11 X
1.
#2100000
0.
#2170000
b10 $
b10 @
b10 B
b0 Y
b0 X
b0 ]
b11 %
b11 ?
b11 V
b101 *
b101 W
1.
#2240000
0.
#2310000
b1 $
b1 @
b1 B
b100 %
b100 ?
b100 V
b1 ]
b10 Y
1.
#2380000
0.
#2450000
b10 ]
b1 X
1.
#2520000
0.
#2590000
b1111 $
b1111 @
b1111 B
1#
b0 Y
b0 X
b0 ]
b101 %
b101 ?
b101 V
b110 *
b110 W
1.
#2660000
0.
#2730000
1!
b11 $
b11 @
b11 B
0#
b110 %
b110 ?
b110 V
b1 ]
b1111 Y
b0 =
1.
#2800000
0.
#2870000
b10 ]
b11 X
1.
#2940000
0.
#3010000
b101 $
b101 @
b101 B
b0 ]
b111 %
b111 ?
b111 V
b111 *
b111 W
1.
#3080000
0.
#3150000
b1000 %
b1000 ?
b1000 V
b1 ]
b101 Y
1.
#3220000
0.
#3290000
b10 ]
b101 X
1.
#3360000
0.
#3430000
b110 $
b110 @
b110 B
1#
b0 Y
b0 X
b0 ]
b1001 %
b1001 ?
b1001 V
b101 '
b101 2
b101 [
b101 &
b101 1
b101 Z
b1000 *
b1000 W
1.
#3500000
0.
#3570000
b0 $
b0 @
b0 B
b101 -
b101 ^
0#
b1010 %
b1010 ?
b1010 V
b1 ]
b110 Y
1"
b101 ,
b101 <
1.
#3640000
0.
#3710000
b0 -
b0 ^
b0 g
0"
b10 ]
1.
#3780000
0.
#3850000
1#
b0 Y
b0 ]
b1011 %
b1011 ?
b1011 V
b0 '
b0 2
b0 [
b110 &
b110 1
b110 Z
b1001 *
b1001 W
1.
#3920000
0.
#3990000
0#
b1100 %
b1100 ?
b1100 V
b1 ]
1.
#4060000
0.
#4130000
b10 ]
1.
#4200000
0.
#4270000
1#
b0 ]
b1101 %
b1101 ?
b1101 V
b0 &
b0 1
b0 Z
b1010 *
b1010 W
1.
#4340000
0.
#4410000
0#
b1110 %
b1110 ?
b1110 V
b1 ]
1.
#4480000
0.
#4550000
b10 ]
1.
#4620000
0.
#4690000
1#
b0 ]
b1111 %
b1111 ?
b1111 V
b1011 *
b1011 W
1.
#4760000
0.
#4830000
0#
b10000 %
b10000 ?
b10000 V
b1 ]
1.
#4900000
0.
#4970000
b10 ]
1.
#5040000
0.
#5110000
1#
b0 ]
b10001 %
b10001 ?
b10001 V
b1100 *
b1100 W
1.
#5180000
0.
#5250000
0#
b10010 %
b10010 ?
b10010 V
b1 ]
1.
#5320000
0.
#5390000
b10 ]
1.
#5460000
0.
#5530000
1#
b0 ]
b10011 %
b10011 ?
b10011 V
b1101 *
b1101 W
1.
#5600000
0.
#5670000
0#
b10100 %
b10100 ?
b10100 V
b1 ]
1.
#5740000
0.
#5810000
b10 ]
1.
#5880000
0.
#5950000
1#
b0 ]
b10101 %
b10101 ?
b10101 V
b1110 *
b1110 W
1.
#6020000
0.
#6090000
0#
b10110 %
b10110 ?
b10110 V
b1 ]
1.
#6160000
0.
#6230000
b10 ]
1.
#6300000
0.
#6370000
1#
b0 ]
b10111 %
b10111 ?
b10111 V
b1111 *
b1111 W
1.
#6440000
0.
#6510000
0#
b11000 %
b11000 ?
b11000 V
b1 ]
1.
#6580000
0.
#6650000
b10 ]
1.
#6720000
0.
#6790000
1#
b0 ]
b11001 %
b11001 ?
b11001 V
b10000 *
b10000 W
1.
#6860000
0.
#6930000
0#
b11010 %
b11010 ?
b11010 V
b1 ]
1.
#7000000
0.
#7070000
b10 ]
1.
#7140000
0.
#7210000
1#
b0 ]
b11011 %
b11011 ?
b11011 V
b10001 *
b10001 W
1.
#7280000
0.
#7350000
0#
b11100 %
b11100 ?
b11100 V
b1 ]
1.
#7420000
0.
#7490000
b10 ]
1.
#7560000
0.
#7630000
1#
b0 ]
b11101 %
b11101 ?
b11101 V
b10010 *
b10010 W
1.
#7700000
0.
#7770000
0#
b11110 %
b11110 ?
b11110 V
b1 ]
1.
#7840000
0.
#7910000
b10 ]
1.
#7980000
0.
#8050000
1#
b0 ]
b11111 %
b11111 ?
b11111 V
b10011 *
b10011 W
1.
#8120000
0.
#8190000
0#
b100000 %
b100000 ?
b100000 V
b1 ]
1.
#8260000
0.
#8330000
b10 ]
1.
#8400000
0.
#8470000
1#
b0 ]
b100001 %
b100001 ?
b100001 V
b10100 *
b10100 W
1.
#8540000
0.
#8610000
0#
b100010 %
b100010 ?
b100010 V
b1 ]
1.
#8680000
0.
#8750000
b10 ]
1.
#8820000
0.
#8890000
1#
b0 ]
b100011 %
b100011 ?
b100011 V
b10101 *
b10101 W
1.
#8960000
0.
#9030000
0#
b100100 %
b100100 ?
b100100 V
b1 ]
1.
#9100000
0.
#9170000
b10 ]
1.
#9240000
0.
#9310000
1#
b0 ]
b100101 %
b100101 ?
b100101 V
b10110 *
b10110 W
1.
#9380000
0.
#9450000
0#
b100110 %
b100110 ?
b100110 V
b1 ]
1.
#9520000
0.
#9590000
b10 ]
1.
#9660000
0.
#9730000
1#
b0 ]
b100111 %
b100111 ?
b100111 V
b10111 *
b10111 W
1.
#9800000
0.
#9870000
0#
b101000 %
b101000 ?
b101000 V
b1 ]
1.
#9940000
0.
#10010000
b10 ]
1.
#10080000
0.
#10150000
1#
b0 ]
b101001 %
b101001 ?
b101001 V
b11000 *
b11000 W
1.
#10220000
0.
#10290000
0#
b101010 %
b101010 ?
b101010 V
b1 ]
1.
#10360000
0.
#10430000
b10 ]
1.
#10500000
0.
#10570000
1#
b0 ]
b101011 %
b101011 ?
b101011 V
b11001 *
b11001 W
1.
#10640000
0.
#10710000
0#
b101100 %
b101100 ?
b101100 V
b1 ]
1.
#10780000
0.
#10850000
b10 ]
1.
#10920000
0.
#10990000
1#
b0 ]
b101101 %
b101101 ?
b101101 V
b11010 *
b11010 W
1.
#11060000
0.
#11130000
0#
b101110 %
b101110 ?
b101110 V
b1 ]
1.
#11200000
0.
#11270000
b10 ]
1.
#11340000
0.
#11410000
1#
b0 ]
b101111 %
b101111 ?
b101111 V
b11011 *
b11011 W
1.
#11480000
0.
#11550000
0#
b110000 %
b110000 ?
b110000 V
b1 ]
1.
#11620000
0.
#11690000
b10 ]
1.
#11760000
0.
#11830000
1#
b0 ]
b110001 %
b110001 ?
b110001 V
b11100 *
b11100 W
1.
#11900000
0.
#11970000
0#
b110010 %
b110010 ?
b110010 V
b1 ]
1.
#12040000
0.
#12110000
b10 ]
1.
#12180000
0.
#12250000
1#
b0 ]
b110011 %
b110011 ?
b110011 V
b11101 *
b11101 W
1.
#12320000
0.
#12390000
0#
b110100 %
b110100 ?
b110100 V
b1 ]
1.
#12460000
0.
#12530000
b10 ]
1.
#12600000
0.
#12670000
1#
b0 ]
b110101 %
b110101 ?
b110101 V
b11110 *
b11110 W
1.
#12740000
0.
#12810000
0#
b110110 %
b110110 ?
b110110 V
b1 ]
1.
#12880000
0.
#12950000
b10 ]
1.
#13020000
0.
#13090000
1#
b0 ]
b110111 %
b110111 ?
b110111 V
b11111 *
b11111 W
1.
#13160000
0.
#13230000
0#
b111000 %
b111000 ?
b111000 V
b1 ]
1.
#13300000
0.
#13370000
b10 ]
1.
#13440000
0.
#13510000
1#
b0 ]
b111001 %
b111001 ?
b111001 V
b100000 *
b100000 W
1.
#13580000
0.
#13650000
0#
b111010 %
b111010 ?
b111010 V
b1 ]
1.
#13720000
0.
#13790000
b10 ]
1.
#13860000
0.
#13930000
1#
b0 ]
b111011 %
b111011 ?
b111011 V
b100001 *
b100001 W
1.
#14000000
0.
#14070000
0#
b111100 %
b111100 ?
b111100 V
b1 ]
1.
#14140000
0.
#14210000
b10 ]
1.
#14280000
0.
#14350000
1#
b0 ]
b111101 %
b111101 ?
b111101 V
b100010 *
b100010 W
1.
#14420000
0.
#14490000
0#
b111110 %
b111110 ?
b111110 V
b1 ]
1.
#14560000
0.
#14630000
b10 ]
1.
#14700000
0.
#14770000
1#
b0 ]
b111111 %
b111111 ?
b111111 V
b100011 *
b100011 W
1.
#14840000
0.
#14910000
0#
b1000000 %
b1000000 ?
b1000000 V
b1 ]
1.
#14980000
0.
#15050000
b10 ]
1.
#15120000
0.
#15190000
1#
b0 ]
b1000001 %
b1000001 ?
b1000001 V
b100100 *
b100100 W
1.
#15260000
0.
#15330000
0#
b1000010 %
b1000010 ?
b1000010 V
b1 ]
1.
#15400000
0.
#15470000
b10 ]
1.
#15540000
0.
#15610000
1#
b0 ]
b1000011 %
b1000011 ?
b1000011 V
b100101 *
b100101 W
1.
#15680000
0.
#15750000
0#
b1000100 %
b1000100 ?
b1000100 V
b1 ]
1.
#15820000
0.
#15890000
b10 ]
1.
#15960000
0.
#16030000
1#
b0 ]
b1000101 %
b1000101 ?
b1000101 V
b100110 *
b100110 W
1.
#16100000
0.
#16170000
0#
b1000110 %
b1000110 ?
b1000110 V
b1 ]
1.
#16240000
0.
#16310000
b10 ]
1.
#16380000
0.
#16450000
1#
b0 ]
b1000111 %
b1000111 ?
b1000111 V
b100111 *
b100111 W
1.
#16520000
0.
#16590000
0#
b1001000 %
b1001000 ?
b1001000 V
b1 ]
1.
#16660000
0.
#16730000
b10 ]
1.
#16800000
0.
#16870000
1#
b0 ]
b1001001 %
b1001001 ?
b1001001 V
b101000 *
b101000 W
1.
#16940000
0.
#17010000
0#
b1001010 %
b1001010 ?
b1001010 V
b1 ]
1.
#17080000
0.
#17150000
b10 ]
1.
#17220000
0.
#17290000
1#
b0 ]
b1001011 %
b1001011 ?
b1001011 V
b101001 *
b101001 W
1.
#17360000
0.
#17430000
0#
b1001100 %
b1001100 ?
b1001100 V
b1 ]
1.
#17500000
0.
#17570000
b10 ]
1.
#17640000
0.
#17710000
1#
b0 ]
b1001101 %
b1001101 ?
b1001101 V
b101010 *
b101010 W
1.
#17780000
0.
#17850000
0#
b1001110 %
b1001110 ?
b1001110 V
b1 ]
1.
#17920000
0.
#17990000
b10 ]
1.
#18060000
0.
#18130000
1#
b0 ]
b1001111 %
b1001111 ?
b1001111 V
b101011 *
b101011 W
1.
#18200000
0.
#18270000
0#
b1010000 %
b1010000 ?
b1010000 V
b1 ]
1.
#18340000
0.
#18410000
b10 ]
1.
#18480000
0.
#18550000
1#
b0 ]
b1010001 %
b1010001 ?
b1010001 V
b101100 *
b101100 W
1.
#18620000
0.
#18690000
0#
b1010010 %
b1010010 ?
b1010010 V
b1 ]
1.
#18760000
0.
#18830000
b10 ]
1.
#18900000
0.
#18970000
1#
b0 ]
b1010011 %
b1010011 ?
b1010011 V
b101101 *
b101101 W
1.
#19040000
0.
#19110000
0#
b1010100 %
b1010100 ?
b1010100 V
b1 ]
1.
#19180000
0.
#19250000
b10 ]
1.
#19320000
0.
#19390000
1#
b0 ]
b1010101 %
b1010101 ?
b1010101 V
b101110 *
b101110 W
1.
#19460000
0.
#19530000
0#
b1010110 %
b1010110 ?
b1010110 V
b1 ]
1.
#19600000
0.
#19670000
b10 ]
1.
#19740000
0.
#19810000
1#
b0 ]
b1010111 %
b1010111 ?
b1010111 V
b101111 *
b101111 W
1.
#19880000
0.
#19950000
0#
b1011000 %
b1011000 ?
b1011000 V
b1 ]
1.
#20020000
0.
#20090000
b10 ]
1.
#20160000
0.
#20230000
1#
b0 ]
b1011001 %
b1011001 ?
b1011001 V
b110000 *
b110000 W
1.
#20300000
0.
#20370000
0#
b1011010 %
b1011010 ?
b1011010 V
b1 ]
1.
#20440000
0.
#20510000
b10 ]
1.
#20580000
0.
#20650000
1#
b0 ]
b1011011 %
b1011011 ?
b1011011 V
b110001 *
b110001 W
1.
#20720000
0.
#20790000
0#
b1011100 %
b1011100 ?
b1011100 V
b1 ]
1.
#20860000
0.
#20930000
b10 ]
1.
#21000000
0.
#21070000
1#
b0 ]
b1011101 %
b1011101 ?
b1011101 V
b110010 *
b110010 W
1.
#21140000
0.
#21210000
0#
b1011110 %
b1011110 ?
b1011110 V
b1 ]
1.
#21280000
0.
#21350000
b10 ]
1.
#21420000
0.
#21490000
1#
b0 ]
b1011111 %
b1011111 ?
b1011111 V
b110011 *
b110011 W
1.
#21560000
0.
#21630000
0#
b1100000 %
b1100000 ?
b1100000 V
b1 ]
1.
#21700000
0.
#21770000
b10 ]
1.
#21840000
0.
#21910000
1#
b0 ]
b1100001 %
b1100001 ?
b1100001 V
b110100 *
b110100 W
1.
#21980000
0.
#22050000
0#
b1100010 %
b1100010 ?
b1100010 V
b1 ]
1.
#22120000
0.
#22190000
b10 ]
1.
#22260000
0.
#22330000
1#
b0 ]
b1100011 %
b1100011 ?
b1100011 V
b110101 *
b110101 W
1.
#22400000
0.
#22470000
0#
b1100100 %
b1100100 ?
b1100100 V
b1 ]
1.
#22540000
0.
#22610000
b10 ]
1.
#22680000
0.
#22750000
1#
b0 ]
b1100101 %
b1100101 ?
b1100101 V
b110110 *
b110110 W
1.
#22820000
0.
#22890000
0#
b1100110 %
b1100110 ?
b1100110 V
b1 ]
1.
#22960000
0.
#23030000
b10 ]
1.
#23100000
0.
#23170000
1#
b0 ]
b1100111 %
b1100111 ?
b1100111 V
b110111 *
b110111 W
1.
#23240000
0.
#23310000
0#
b1101000 %
b1101000 ?
b1101000 V
b1 ]
1.
#23380000
0.
#23450000
b10 ]
1.
#23520000
0.
#23590000
1#
b0 ]
b1101001 %
b1101001 ?
b1101001 V
b111000 *
b111000 W
1.
#23660000
0.
#23730000
0#
b1101010 %
b1101010 ?
b1101010 V
b1 ]
1.
#23800000
0.
#23870000
b10 ]
1.
#23940000
0.
#24010000
1#
b0 ]
b1101011 %
b1101011 ?
b1101011 V
b111001 *
b111001 W
1.
#24080000
0.
#24150000
0#
b1101100 %
b1101100 ?
b1101100 V
b1 ]
1.
#24220000
0.
#24290000
b10 ]
1.
#24360000
0.
#24430000
1#
b0 ]
b1101101 %
b1101101 ?
b1101101 V
b111010 *
b111010 W
1.
#24500000
0.
#24570000
0#
b1101110 %
b1101110 ?
b1101110 V
b1 ]
1.
#24640000
0.
#24710000
b10 ]
1.
#24780000
0.
#24850000
1#
b0 ]
b1101111 %
b1101111 ?
b1101111 V
b111011 *
b111011 W
1.
#24920000
0.
#24990000
0#
b1110000 %
b1110000 ?
b1110000 V
b1 ]
1.
#25060000
0.
#25130000
b10 ]
1.
#25200000
0.
#25270000
1#
b0 ]
b1110001 %
b1110001 ?
b1110001 V
b111100 *
b111100 W
1.
#25340000
0.
#25410000
0#
b1110010 %
b1110010 ?
b1110010 V
b1 ]
1.
