src/prog_cntr.v
module prog_cntr(
    input wire clk,
    input wire [7:0] instruction_byte,
    output reg [3:0] address = 1,
    output reg [3:0] op_code = 0,
    output reg [7:0] operand,
    input wire start_enable,
    output reg we = 0,
    output reg [7:0] counter = 0,
    output reg [7:0] rom_address = 0,
    input wire [7:0] rom_data_in
);

reg [7:0] op ;
reg [7:0] num ;
reg [7:0] rom_data ;

localparam inst_1 = 0 ;
localparam inst_2 = 1 ;
localparam exe = 2 ;
localparam mem_wait = 3;
localparam mem_exec = 4;

localparam ADD = 8'd1 ;
localparam SUB = 8'd2;
localparam SHIFT_LEFT = 8'd3;
localparam SHIFT_RIGHT = 8'd4;
localparam OUT = 8'd5;
localparam CLEAN = 8'd6;
localparam JUMP = 8'd7;
localparam ADD_MEM = 8'd8;
localparam SUB_MEM = 8'd9;
localparam SHIFT_LEFT_MEM = 8'd10;
localparam SHIFT_RIGHT_MEM = 8'd11;

reg [2:0] state = 2'd0 ;


always @(posedge clk ) begin
    if(start_enable)begin
        case (state)
            inst_1 : begin
                op <= instruction_byte;
                state <= inst_2;
                address <= address + 8'd1;
                we <= 0;         
            end
            inst_2 : begin
                num <= instruction_byte;
                state <= exe;
            end
            exe : begin
                counter <= counter + 8'd1;
                if(op <= 8'd6) begin
                    op_code <= (op & 4'hF);
                    operand <= num;
                    address <= address + 8'd1;
                    state <= inst_1;
                    num <= 0;
                    op <= 0;
                    we <= 1;
                end
                else if(op >= 8'd7) begin
                    case (op)
                        ADD_MEM : begin
                            state <= mem_wait;
                            rom_address <= num;
                            op <= ADD;
                        end
                        SUB_MEM : begin
                            state <= mem_wait;
                            rom_address <= num;
                            op <= SUB;
                        end
                        SHIFT_LEFT_MEM : begin
                            state <= mem_wait;
                            rom_address <= num;
                            op <= SHIFT_LEFT;
                        end
                        SHIFT_RIGHT_MEM : begin
                            state <= mem_wait;
                            rom_address <= num;
                            op <= SHIFT_RIGHT;
                        end
                        JUMP : begin
                            address <= num;
                            state <= inst_1;
                            num <= 0;
                            op <= 0;
                        end
                        default: begin 
                            state <= inst_1;
                        end
                    endcase
                end
            end
            mem_wait : begin
                state <= mem_exec;
                num <= rom_data_in;
            end
            mem_exec : begin
                state <= inst_1;
                operand <= num;
                op_code <= op;
                address <= address + 8'd1;
                num <= 0;
                op <= 0;
                we <= 1;
            end  
            default: begin 
                state <= inst_1;
                op_code <= 0;
                operand <= 0;
            end
        endcase
    end
end
endmodule

src/inst_rom.v
module inst_rom (
    input wire [3:0] address ,
    output reg [7:0] instruction_byte = 0
);

reg [7:0] mem [0:255];
        integer i;
initial begin

    for (i = 0 ; i < 256 ; i = i+1 ) begin
        mem[i] = 0;
    end
end
initial begin
    mem[8'h01] = 8'h06; // CLEAN
    mem[8'h02] = 8'h00; 
    mem[8'h03] = 8'h01; // ADD
    mem[8'h04] = 8'h01; // num = 1
    mem[8'h05] = 8'h05; // OUT
    mem[8'h06] = 8'h00;
    mem[8'h07] = 8'h03; // SHIFT_LEFT
    mem[8'h08] = 8'h01; // num = 1
    mem[8'h09] = 8'h05; // OUT
    mem[8'h0A] = 8'h00;
    mem[8'd11] = 8'd7; // JUMP TO
    mem[8'd12] = 8'd7; // address 7
end

always @(*) begin
    instruction_byte = mem[address];
end
    
endmodule

src/accumulator.v
module accumulator(
    input wire clk,
    input wire [3:0] op,
    input wire [7:0] num,
    output reg [7:0] result = 0,
    input wire we,
    output reg [7:0] address_mem
);

reg [7:0] data = 8'd0 ;

localparam ADD = 4'd1 ;
localparam SUB = 4'd2;
localparam SHIFT_LEFT = 4'd3;
localparam SHIFT_RIGHT = 4'd4;
localparam OUT = 4'd5;
localparam CLEAN = 4'd6;

always @(posedge clk ) begin
    if (op != 0 && we) begin
        case (op)
            ADD : begin
                data <= data + num;
            end
            SUB : begin
                data <= data - num;
            end
            SHIFT_LEFT : begin
                data <= data << (num & 8'h7);
            end
            SHIFT_RIGHT : begin
                data <= data >> (num & 8'h7);
            end
            OUT : begin
                result <= data;
                address_mem <= num;
            end
            CLEAN : begin
                result <= 8'd0;
                data <= 8'd0;
            end 
            default: begin
                data <= data;
            end
        endcase
    end
    else begin
        result <= result;
    end
end
endmodule

src/tb_cpu.v
`timescale 1ns/1ps

module tb_cpu();

reg clk;
wire [3:0] address;
wire [7:0] result;
wire [7:0] instruction_byte;
wire [3:0] op;
wire [7:0] num;
reg start_enable;
wire we;
wire [7:0] counter;

accumulator uua(
    .clk(clk),
    .op(op),
    .num(num),
    .result(result),
    .we(we)
);

inst_rom uub(
    .address(address),
    .instruction_byte(instruction_byte)
);

prog_cntr uuc(
    .clk(clk),
    .address(address),
    .op_code(op),
    .operand(num),
    .instruction_byte(instruction_byte),
    .start_enable(start_enable),
    .we(we),
    .counter(counter)
);

always #70 clk = ~clk;

initial begin
    clk = 0;
    start_enable = 0;
    #100
    start_enable = 1;
    @(posedge clk);
    wait (counter == 30);
    $finish;
end

initial begin
    $dumpfile("tb_cpu.vcd");
    $dumpvars(0,tb_cpu);
end
endmodule

src/tb_cpu.vcd
$date
	Wed Sep 23 00:37:49 2026
$end
$version
	Icarus Verilog
$end
$timescale
	1ps
$end
$scope module tb_cpu $end
$var wire 1 ! we $end
$var wire 8 " result [7:0] $end
$var wire 4 # op [3:0] $end
$var wire 8 $ num [7:0] $end
$var wire 8 % instruction_byte [7:0] $end
$var wire 8 & counter [7:0] $end
$var wire 4 ' address [3:0] $end
$var reg 1 ( clk $end
$var reg 1 ) start_enable $end
$scope module uua $end
$var wire 1 ( clk $end
$var wire 1 ! we $end
$var wire 4 * op [3:0] $end
$var wire 8 + num [7:0] $end
$var parameter 4 , ADD $end
$var parameter 4 - CLEAN $end
$var parameter 4 . OUT $end
$var parameter 4 / SHIFT_LEFT $end
$var parameter 4 0 SHIFT_RIGHT $end
$var parameter 4 1 SUB $end
$var reg 8 2 address_mem [7:0] $end
$var reg 8 3 data [7:0] $end
$var reg 8 4 result [7:0] $end
$upscope $end
$scope module uub $end
$var wire 4 5 address [3:0] $end
$var reg 8 6 instruction_byte [7:0] $end
$var integer 32 7 i [31:0] $end
$upscope $end
$scope module uuc $end
$var wire 1 ( clk $end
$var wire 8 8 instruction_byte [7:0] $end
$var wire 8 9 rom_data_in [7:0] $end
$var wire 1 ) start_enable $end
$var parameter 8 : ADD $end
$var parameter 8 ; ADD_MEM $end
$var parameter 8 < CLEAN $end
$var parameter 8 = JUMP $end
$var parameter 8 > OUT $end
$var parameter 8 ? SHIFT_LEFT $end
$var parameter 8 @ SHIFT_LEFT_MEM $end
$var parameter 8 A SHIFT_RIGHT $end
$var parameter 8 B SHIFT_RIGHT_MEM $end
$var parameter 8 C SUB $end
$var parameter 8 D SUB_MEM $end
$var parameter 32 E exe $end
$var parameter 32 F inst_1 $end
$var parameter 32 G inst_2 $end
$var parameter 32 H mem_exec $end
$var parameter 32 I mem_wait $end
$var reg 4 J address [3:0] $end
$var reg 8 K counter [7:0] $end
$var reg 8 L num [7:0] $end
$var reg 8 M op [7:0] $end
$var reg 4 N op_code [3:0] $end
$var reg 8 O operand [7:0] $end
$var reg 8 P rom_address [7:0] $end
$var reg 3 Q state [2:0] $end
$var reg 1 ! we $end
$upscope $end
$upscope $end
$enddefinitions $end
$comment Show the parameter values. $end
$dumpall
b11 I
b100 H
b1 G
b0 F
b10 E
b1001 D
b10 C
b1011 B
b100 A
b1010 @
b11 ?
b101 >
b111 =
b110 <
b1000 ;
b1 :
b10 1
b100 0
b11 /
b101 .
b110 -
b1 ,
$end
#0
$dumpvars
b0 Q
b0 P
bx O
b0 N
bx M
bx L
b0 K
b1 J
bz 9
b110 8
b100000000 7
b110 6
b1 5
b0 4
b0 3
bx 2
bx +
b0 *
0)
0(
b1 '
b0 &
b110 %
bx $
b0 #
b0 "
0!
$end
#70000
1(
#100000
1)
#140000
0(
#210000
b0 %
b0 6
b0 8
b10 '
b10 5
b10 J
b1 Q
b110 M
1(
#280000
0(
#350000
b10 Q
b0 L
1(
#420000
0(
#490000
b1 %
b1 6
b1 8
1!
b0 M
b0 Q
b11 '
b11 5
b11 J
b0 $
b0 +
b0 O
b110 #
b110 *
b110 N
b1 &
b1 K
1(
#560000
0(
#630000
0!
b100 '
b100 5
b100 J
b1 Q
b1 M
1(
#700000
0(
#770000
b10 Q
b1 L
1(
#840000
0(
#910000
b101 %
b101 6
b101 8
1!
b0 M
b0 L
b0 Q
b101 '
b101 5
b101 J
b1 $
b1 +
b1 O
b1 #
b1 *
b1 N
b10 &
b10 K
1(
#980000
0(
#1050000
b0 %
b0 6
b0 8
0!
b110 '
b110 5
b110 J
b1 Q
b101 M
b1 3
1(
#1120000
0(
#1190000
b10 Q
1(
#1260000
0(
#1330000
b11 %
b11 6
b11 8
1!
b0 M
b0 Q
b111 '
b111 5
b111 J
b0 $
b0 +
b0 O
b101 #
b101 *
b101 N
b11 &
b11 K
1(
#1400000
0(
#1470000
b1 %
b1 6
b1 8
b0 2
b1 "
b1 4
0!
b1000 '
b1000 5
b1000 J
b1 Q
b11 M
1(
#1540000
0(
#1610000
b10 Q
b1 L
1(
#1680000
0(
#1750000
b101 %
b101 6
b101 8
1!
b0 M
b0 L
b0 Q
b1001 '
b1001 5
b1001 J
b1 $
b1 +
b1 O
b11 #
b11 *
b11 N
b100 &
b100 K
1(
#1820000
0(
#1890000
b0 %
b0 6
b0 8
0!
b1010 '
b1010 5
b1010 J
b1 Q
b101 M
b10 3
1(
#1960000
0(
#2030000
b10 Q
1(
#2100000
0(
#2170000
b111 %
b111 6
b111 8
1!
b0 M
b0 Q
b1011 '
b1011 5
b1011 J
b0 $
b0 +
b0 O
b101 #
b101 *
b101 N
b101 &
b101 K
1(
#2240000
0(
#2310000
b10 "
b10 4
0!
b1100 '
b1100 5
b1100 J
b1 Q
b111 M
1(
#2380000
0(
#2450000
b10 Q
b111 L
1(
#2520000
0(
#2590000
b11 %
b11 6
b11 8
b0 M
b0 L
b0 Q
b111 '
b111 5
b111 J
b110 &
b110 K
1(
#2660000
0(
#2730000
b1 %
b1 6
b1 8
b1000 '
b1000 5
b1000 J
b1 Q
b11 M
1(
#2800000
0(
#2870000
b10 Q
b1 L
1(
#2940000
0(
#3010000
b101 %
b101 6
b101 8
1!
b0 M
b0 L
b0 Q
b1001 '
b1001 5
b1001 J
b1 $
b1 +
b1 O
b11 #
b11 *
b11 N
b111 &
b111 K
1(
#3080000
0(
#3150000
b0 %
b0 6
b0 8
b100 3
0!
b1010 '
b1010 5
b1010 J
b1 Q
b101 M
1(
#3220000
0(
#3290000
b10 Q
1(
#3360000
0(
#3430000
b111 %
b111 6
b111 8
1!
b0 M
b0 Q
b1011 '
b1011 5
b1011 J
b0 $
b0 +
b0 O
b101 #
b101 *
b101 N
b1000 &
b1000 K
1(
#3500000
0(
#3570000
0!
b1100 '
b1100 5
b1100 J
b1 Q
b111 M
b100 "
b100 4
1(
#3640000
0(
#3710000
b10 Q
b111 L
1(
#3780000
0(
#3850000
b11 %
b11 6
b11 8
b0 M
b0 L
b0 Q
b111 '
b111 5
b111 J
b1001 &
b1001 K
1(
#3920000
0(
#3990000
b1 %
b1 6
b1 8
b1000 '
b1000 5
b1000 J
b1 Q
b11 M
1(
#4060000
0(
#4130000
b10 Q
b1 L
1(
#4200000
0(
#4270000
b101 %
b101 6
b101 8
1!
b0 M
b0 L
b0 Q
b1001 '
b1001 5
b1001 J
b1 $
b1 +
b1 O
b11 #
b11 *
b11 N
b1010 &
b1010 K
1(
#4340000
0(
#4410000
b0 %
b0 6
b0 8
0!
b1010 '
b1010 5
b1010 J
b1 Q
b101 M
b1000 3
1(
#4480000
0(
#4550000
b10 Q
1(
#4620000
0(
#4690000
b111 %
b111 6
b111 8
1!
b0 M
b0 Q
b1011 '
b1011 5
b1011 J
b0 $
b0 +
b0 O
b101 #
b101 *
b101 N
b1011 &
b1011 K
1(
#4760000
0(
#4830000
b1000 "
b1000 4
0!
b1100 '
b1100 5
b1100 J
b1 Q
b111 M
1(
#4900000
0(
#4970000
b10 Q
b111 L
1(
#5040000
0(
#5110000
b11 %
b11 6
b11 8
b0 M
b0 L
b0 Q
b111 '
b111 5
b111 J
b1100 &
b1100 K
1(
#5180000
0(
#5250000
b1 %
b1 6
b1 8
b1000 '
b1000 5
b1000 J
b1 Q
b11 M
1(
#5320000
0(
#5390000
b10 Q
b1 L
1(
#5460000
0(
#5530000
b101 %
b101 6
b101 8
1!
b0 M
b0 L
b0 Q
b1001 '
b1001 5
b1001 J
b1 $
b1 +
b1 O
b11 #
b11 *
b11 N
b1101 &
b1101 K
1(
#5600000
0(
#5670000
b0 %
b0 6
b0 8
b10000 3
0!
b1010 '
b1010 5
b1010 J
b1 Q
b101 M
1(
#5740000
0(
#5810000
b10 Q
1(
#5880000
0(
#5950000
b111 %
b111 6
b111 8
1!
b0 M
b0 Q
b1011 '
b1011 5
b1011 J
b0 $
b0 +
b0 O
b101 #
b101 *
b101 N
b1110 &
b1110 K
1(
#6020000
0(
#6090000
0!
b1100 '
b1100 5
b1100 J
b1 Q
b111 M
b10000 "
b10000 4
1(
#6160000
0(
#6230000
b10 Q
b111 L
1(
#6300000
0(
#6370000
b11 %
b11 6
b11 8
b0 M
b0 L
b0 Q
b111 '
b111 5
b111 J
b1111 &
b1111 K
1(
#6440000
0(
#6510000
b1 %
b1 6
b1 8
b1000 '
b1000 5
b1000 J
b1 Q
b11 M
1(
#6580000
0(
#6650000
b10 Q
b1 L
1(
#6720000
0(
#6790000
b101 %
b101 6
b101 8
1!
b0 M
b0 L
b0 Q
b1001 '
b1001 5
b1001 J
b1 $
b1 +
b1 O
b11 #
b11 *
b11 N
b10000 &
b10000 K
1(
#6860000
0(
#6930000
b0 %
b0 6
b0 8
0!
b1010 '
b1010 5
b1010 J
b1 Q
b101 M
b100000 3
1(
#7000000
0(
#7070000
b10 Q
1(
#7140000
0(
#7210000
b111 %
b111 6
b111 8
1!
b0 M
b0 Q
b1011 '
b1011 5
b1011 J
b0 $
b0 +
b0 O
b101 #
b101 *
b101 N
b10001 &
b10001 K
1(
#7280000
0(
#7350000
b100000 "
b100000 4
0!
b1100 '
b1100 5
b1100 J
b1 Q
b111 M
1(
#7420000
0(
#7490000
b10 Q
b111 L
1(
#7560000
0(
#7630000
b11 %
b11 6
b11 8
b0 M
b0 L
b0 Q
b111 '
b111 5
b111 J
b10010 &
b10010 K
1(
#7700000
0(
#7770000
b1 %
b1 6
b1 8
b1000 '
b1000 5
b1000 J
b1 Q
b11 M
1(
#7840000
0(
#7910000
b10 Q
b1 L
1(
#7980000
0(
#8050000
b101 %
b101 6
b101 8
1!
b0 M
b0 L
b0 Q
b1001 '
b1001 5
b1001 J
b1 $
b1 +
b1 O
b11 #
b11 *
b11 N
b10011 &
b10011 K
1(
#8120000
0(
#8190000
b0 %
b0 6
b0 8
b1000000 3
0!
b1010 '
b1010 5
b1010 J
b1 Q
b101 M
1(
#8260000
0(
#8330000
b10 Q
1(
#8400000
0(
#8470000
b111 %
b111 6
b111 8
1!
b0 M
b0 Q
b1011 '
b1011 5
b1011 J
b0 $
b0 +
b0 O
b101 #
b101 *
b101 N
b10100 &
b10100 K
1(
#8540000
0(
#8610000
0!
b1100 '
b1100 5
b1100 J
b1 Q
b111 M
b1000000 "
b1000000 4
1(
#8680000
0(
#8750000
b10 Q
b111 L
1(
#8820000
0(
#8890000
b11 %
b11 6
b11 8
b0 M
b0 L
b0 Q
b111 '
b111 5
b111 J
b10101 &
b10101 K
1(
#8960000
0(
#9030000
b1 %
b1 6
b1 8
b1000 '
b1000 5
b1000 J
b1 Q
b11 M
1(
#9100000
0(
#9170000
b10 Q
b1 L
1(
#9240000
0(
#9310000
b101 %
b101 6
b101 8
1!
b0 M
b0 L
b0 Q
b1001 '
b1001 5
b1001 J
b1 $
b1 +
b1 O
b11 #
b11 *
b11 N
b10110 &
b10110 K
1(
#9380000
0(
#9450000
b0 %
b0 6
b0 8
0!
b1010 '
b1010 5
b1010 J
b1 Q
b101 M
b10000000 3
1(
#9520000
0(
#9590000
b10 Q
1(
#9660000
0(
#9730000
b111 %
b111 6
b111 8
1!
b0 M
b0 Q
b1011 '
b1011 5
b1011 J
b0 $
b0 +
b0 O
b101 #
b101 *
b101 N
b10111 &
b10111 K
1(
#9800000
0(
#9870000
b10000000 "
b10000000 4
0!
b1100 '
b1100 5
b1100 J
b1 Q
b111 M
1(
#9940000
0(
#10010000
b10 Q
b111 L
1(
#10080000
0(
#10150000
b11 %
b11 6
b11 8
b0 M
b0 L
b0 Q
b111 '
b111 5
b111 J
b11000 &
b11000 K
1(
#10220000
0(
#10290000
b1 %
b1 6
b1 8
b1000 '
b1000 5
b1000 J
b1 Q
b11 M
1(
#10360000
0(
#10430000
b10 Q
b1 L
1(
#10500000
0(
#10570000
b101 %
b101 6
b101 8
1!
b0 M
b0 L
b0 Q
b1001 '
b1001 5
b1001 J
b1 $
b1 +
b1 O
b11 #
b11 *
b11 N
b11001 &
b11001 K
1(
#10640000
0(
#10710000
b0 %
b0 6
b0 8
b0 3
0!
b1010 '
b1010 5
b1010 J
b1 Q
b101 M
1(
#10780000
0(
#10850000
b10 Q
1(
#10920000
0(
#10990000
b111 %
b111 6
b111 8
1!
b0 M
b0 Q
b1011 '
b1011 5
b1011 J
b0 $
b0 +
b0 O
b101 #
b101 *
b101 N
b11010 &
b11010 K
1(
#11060000
0(
#11130000
0!
b1100 '
b1100 5
b1100 J
b1 Q
b111 M
b0 "
b0 4
1(
#11200000
0(
#11270000
b10 Q
b111 L
1(
#11340000
0(
#11410000
b11 %
b11 6
b11 8
b0 M
b0 L
b0 Q
b111 '
b111 5
b111 J
b11011 &
b11011 K
1(
#11480000
0(
#11550000
b1 %
b1 6
b1 8
b1000 '
b1000 5
b1000 J
b1 Q
b11 M
1(
#11620000
0(
#11690000
b10 Q
b1 L
1(
#11760000
0(
#11830000
b101 %
b101 6
b101 8
1!
b0 M
b0 L
b0 Q
b1001 '
b1001 5
b1001 J
b1 $
b1 +
b1 O
b11 #
b11 *
b11 N
b11100 &
b11100 K
1(
#11900000
0(
#11970000
b0 %
b0 6
b0 8
0!
b1010 '
b1010 5
b1010 J
b1 Q
b101 M
1(
#12040000
0(
#12110000
b10 Q
1(
#12180000
0(
#12250000
b111 %
b111 6
b111 8
1!
b0 M
b0 Q
b1011 '
b1011 5
b1011 J
b0 $
b0 +
b0 O
b101 #
b101 *
b101 N
b11101 &
b11101 K
1(
#12320000
0(
#12390000
0!
b1100 '
b1100 5
b1100 J
b1 Q
b111 M
1(
#12460000
0(
#12530000
b10 Q
b111 L
1(
#12600000
0(
#12670000
b11 %
b11 6
b11 8
b0 M
b0 L
b0 Q
b111 '
b111 5
b111 J
b11110 &
b11110 K
1(
